postnl_checkout/__init__.py
postnl_checkout/client.py
postnl_checkout/exceptions.py
postnl_checkout/utils.py
postnl_checkout/contrib/__init__.py
postnl_checkout/contrib/django_postnl_checkout/__init__.py
postnl_checkout/contrib/django_postnl_checkout/admin.py
postnl_checkout/contrib/django_postnl_checkout/models.py
postnl_checkout/contrib/django_postnl_checkout/settings.py
postnl_checkout/contrib/django_postnl_checkout/utils.py
postnl_checkout/contrib/django_postnl_checkout/views.py
postnl_checkout/contrib/django_postnl_checkout/migrations/0001_initial.py
postnl_checkout/contrib/django_postnl_checkout/migrations/__init__.py
postnl_checkout/contrib/django_postnl_checkout/templatetags/__init__.py
postnl_checkout/contrib/django_postnl_checkout/templatetags/postnl_checkout_tags.py
python_postnl_checkout-0.9.dist-info/DESCRIPTION.rst
python_postnl_checkout-0.9.dist-info/METADATA
python_postnl_checkout-0.9.dist-info/RECORD
python_postnl_checkout-0.9.dist-info/WHEEL
python_postnl_checkout-0.9.dist-info/metadata.json
python_postnl_checkout-0.9.dist-info/pbr.json
python_postnl_checkout-0.9.dist-info/top_level.txt
