Metadata-Version: 2.0
Name: python-postnl-checkout
Version: 0.9
Summary: PostNL checkout support for Django.
Home-page: https://github.com/dokterbob/python-postnl-checkout/
Author: Mathijs de Bruin
Author-email: mathijs@mathijsfietst.nl
License: AGPL
Platform: UNKNOWN
Classifier: Development Status :: 4 - Beta
Classifier: Environment :: Web Environment
Classifier: Framework :: Django
Classifier: Intended Audience :: Developers
Classifier: License :: OSI Approved :: GNU Affero General Public License v3
Classifier: Operating System :: OS Independent
Classifier: Programming Language :: Python
Classifier: Topic :: Utilities
Requires-Dist: suds
Requires-Dist: suds-requests
Provides-Extra: Django
Requires-Dist: Django (>=1.8.13); extra == 'Django'
Requires-Dist: django-jsonfield (>=0.9.18); extra == 'Django'
